[{"id": "442734829", "uid": "633013", "tags": {"building": "yes"}, "user": "Honning", "version": 2}, {"id": "442734830", "uid": "633013", "tags": {"building": "yes"}, "user": "Honning", "version": 2}, {"id": "442734833", "uid": "633013", "tags": {"building": "yes"}, "user": "Honning", "version": 2}, {"id": "442734835", "uid": "633013", "tags": {"building": "yes"}, "user": "Honning", "version": 2}, {"id": "442735137", "uid": "633013", "tags": {"building": "yes"}, "user": "Honning", "version": 2}, {"id": "442750746", "uid": "633013", "tags": {"building": "yes"}, "user": "Honning", "version": 2}, {"id": "442750747", "uid": "633013", "tags": {"building": "yes"}, "user": "Honning", "version": 2}, {"id": "442750749", "uid": "633013", "tags": {"building": "yes"}, "user": "Honning", "version": 2}, {"id": "442750796", "uid": "633013", "tags": {"building": "yes"}, "user": "Honning", "version": 2}, {"id": "442750803", "uid": "633013", "tags": {"building": "yes"}, "user": "Honning", "version": 2}, {"id": "442753660", "uid": "633013", "tags": {"building": "yes"}, "user": "Honning", "version": 2}, {"id": "443394681", "uid": "633013", "tags": {"building": "yes"}, "user": "Honning", "version": 2}, {"id": "444963018", "uid": "633013", "tags": {"building": "yes"}, "user": "Honning", "version": 2}, {"tags": {"building": "yes"}, "nodes": [{"lat": -1.1716816, "id": "4674893268", "lon": 34.3760528}, {"lat": -1.1716918, "id": "4674893269", "lon": 34.3760984}, {"lat": -1.1717265, "id": "4674893270", "lon": 34.3760906}, {"lat": -1.1717163, "id": "4674893271", "lon": 34.3760451}, {"lat": -1.1716816, "id": "4674893268", "lon": 34.3760528}], "id": "473362777", "uid": "633013", "version": 1, "user": "Honning"}, {"tags": {"building": "yes"}, "nodes": [{"lat": -1.1722273, "id": "4674893272", "lon": 34.3755639}, {"lat": -1.1722351, "id": "4674893273", "lon": 34.3755995}, {"lat": -1.1722636, "id": "4674893274", "lon": 34.3755934}, {"lat": -1.1722559, "id": "4674893275", "lon": 34.3755577}, {"lat": -1.1722273, "id": "4674893272", "lon": 34.3755639}], "id": "473362779", "uid": "633013", "version": 1, "user": "Honning"}, {"tags": {"building": "yes"}, "nodes": [{"lat": -1.1722092, "id": "4674893284", "lon": 34.3749254}, {"lat": -1.1722136, "id": "4674893285", "lon": 34.3749207}, {"lat": -1.1722162, "id": "4674893286", "lon": 34.3749148}, {"lat": -1.1722167, "id": "4674893287", "lon": 34.3749084}, {"lat": -1.1722152, "id": "4674893288", "lon": 34.3749021}, {"lat": -1.1722117, "id": "4674894489", "lon": 34.3748967}, {"lat": -1.1722067, "id": "4674894490", "lon": 34.3748928}, {"lat": -1.1722006, "id": "4674894491", "lon": 34.3748906}, {"lat": -1.1721942, "id": "4674894492", "lon": 34.3748906}, {"lat": -1.1721881, "id": "4674894493", "lon": 34.3748926}, {"lat": -1.172183, "id": "4674894494", "lon": 34.3748965}, {"lat": -1.1721794, "id": "4674893276", "lon": 34.3749019}, {"lat": -1.1721778, "id": "4674893279", "lon": 34.3749081}, {"lat": -1.1721782, "id": "4674893280", "lon": 34.3749146}, {"lat": -1.1721808, "id": "4674893281", "lon": 34.3749205}, {"lat": -1.1721852, "id": "4674893282", "lon": 34.3749253}, {"lat": -1.1721908, "id": "4674893283", "lon": 34.3749284}, {"lat": -1.1721972, "id": "4674893277", "lon": 34.3749295}, {"lat": -1.1722036, "id": "4674893278", "lon": 34.3749284}, {"lat": -1.1722092, "id": "4674893284", "lon": 34.3749254}], "id": "473362781", "uid": "633013", "version": 1, "user": "Honning"}, {"tags": {"building": "yes"}, "nodes": [{"lat": -1.1745532, "id": "4674894495", "lon": 34.376194}, {"lat": -1.1745545, "id": "4674894496", "lon": 34.376235}, {"lat": -1.174586, "id": "4674894497", "lon": 34.3762341}, {"lat": -1.1745847, "id": "4674894498", "lon": 34.376193}, {"lat": -1.1745532, "id": "4674894495", "lon": 34.376194}], "id": "473362784", "uid": "633013", "version": 1, "user": "Honning"}, {"tags": {"building": "yes"}, "nodes": [{"lat": -1.1664285, "id": "4674894510", "lon": 34.3824719}, {"lat": -1.1664335, "id": "4674894511", "lon": 34.3824797}, {"lat": -1.1664355, "id": "4674894512", "lon": 34.3824887}, {"lat": -1.1664345, "id": "4674894513", "lon": 34.3824979}, {"lat": -1.1664304, "id": "4674894514", "lon": 34.3825063}, {"lat": -1.1664238, "id": "4674894515", "lon": 34.3825128}, {"lat": -1.1664154, "id": "4674894516", "lon": 34.3825167}, {"lat": -1.1664061, "id": "4674894517", "lon": 34.3825175}, {"lat": -1.1663971, "id": "4674894518", "lon": 34.3825153}, {"lat": -1.1663894, "id": "4674894519", "lon": 34.3825102}, {"lat": -1.1663838, "id": "4674894520", "lon": 34.3825028}, {"lat": -1.166381, "id": "4674894502", "lon": 34.382494}, {"lat": -1.1663812, "id": "4674894505", "lon": 34.3824855}, {"lat": -1.1663839, "id": "4674894506", "lon": 34.3824775}, {"lat": -1.166389, "id": "4674894507", "lon": 34.3824706}, {"lat": -1.1663959, "id": "4674894508", "lon": 34.3824657}, {"lat": -1.166404, "id": "4674894509", "lon": 34.3824631}, {"lat": -1.1664125, "id": "4674894503", "lon": 34.3824631}, {"lat": -1.1664212, "id": "4674894504", "lon": 34.3824661}, {"lat": -1.1664285, "id": "4674894510", "lon": 34.3824719}], "id": "473362787", "uid": "633013", "version": 1, "user": "Honning"}, {"tags": {"building": "yes"}, "nodes": [{"lat": -1.1703812, "id": "4674894523", "lon": 34.3846967}, {"lat": -1.1703968, "id": "4674894524", "lon": 34.3847386}, {"lat": -1.170435, "id": "4674894525", "lon": 34.3847243}, {"lat": -1.1704194, "id": "4674894526", "lon": 34.3846825}, {"lat": -1.1703812, "id": "4674894523", "lon": 34.3846967}], "id": "473362788", "uid": "633013", "version": 1, "user": "Honning"}, {"tags": {"building": "yes"}, "nodes": [{"lat": -1.1696157, "id": "4674894527", "lon": 34.3851147}, {"lat": -1.1696234, "id": "4674894528", "lon": 34.3851481}, {"lat": -1.1696517, "id": "4674894529", "lon": 34.3851417}, {"lat": -1.1696441, "id": "4674894530", "lon": 34.3851083}, {"lat": -1.1696157, "id": "4674894527", "lon": 34.3851147}], "id": "473362789", "uid": "633013", "version": 1, "user": "Honning"}, {"tags": {"building": "yes"}, "nodes": [{"lat": -1.169438, "id": "4674894531", "lon": 34.3860393}, {"lat": -1.1694671, "id": "4674894532", "lon": 34.3860857}, {"lat": -1.1695075, "id": "4674894533", "lon": 34.3860603}, {"lat": -1.1694784, "id": "4674894534", "lon": 34.386014}, {"lat": -1.169438, "id": "4674894531", "lon": 34.3860393}], "id": "473362790", "uid": "633013", "version": 1, "user": "Honning"}, {"tags": {"building": "yes"}, "nodes": [{"lat": -1.1693408, "id": "4674894535", "lon": 34.3860446}, {"lat": -1.1693606, "id": "4674894536", "lon": 34.3860883}, {"lat": -1.1693996, "id": "4674894537", "lon": 34.3860706}, {"lat": -1.1693798, "id": "4674894538", "lon": 34.3860269}, {"lat": -1.1693408, "id": "4674894535", "lon": 34.3860446}], "id": "473362791", "uid": "633013", "version": 1, "user": "Honning"}, {"tags": {"building": "yes"}, "nodes": [{"lat": -1.1693364, "id": "4674894547", "lon": 34.3859959}, {"lat": -1.1693405, "id": "4674894548", "lon": 34.3860019}, {"lat": -1.1693424, "id": "4674894549", "lon": 34.3860089}, {"lat": -1.1693421, "id": "4674894550", "lon": 34.3860161}, {"lat": -1.1693394, "id": "4674894551", "lon": 34.3860229}, {"lat": -1.1693348, "id": "4674894552", "lon": 34.3860285}, {"lat": -1.1693286, "id": "4674894553", "lon": 34.3860323}, {"lat": -1.1693216, "id": "4674894554", "lon": 34.3860339}, {"lat": -1.1693144, "id": "4674894555", "lon": 34.3860333}, {"lat": -1.1693077, "id": "4674894556", "lon": 34.3860304}, {"lat": -1.1693024, "id": "4674894557", "lon": 34.3860255}, {"lat": -1.1692988, "id": "4674894539", "lon": 34.3860192}, {"lat": -1.1692974, "id": "4674894542", "lon": 34.3860115}, {"lat": -1.1692988, "id": "4674894543", "lon": 34.3860038}, {"lat": -1.1693026, "id": "4674894544", "lon": 34.385997}, {"lat": -1.1693086, "id": "4674894545", "lon": 34.3859919}, {"lat": -1.169316, "id": "4674894546", "lon": 34.3859892}, {"lat": -1.1693238, "id": "4674894540", "lon": 34.3859892}, {"lat": -1.1693306, "id": "4674894541", "lon": 34.3859915}, {"lat": -1.1693364, "id": "4674894547", "lon": 34.3859959}], "id": "473362792", "uid": "633013", "version": 1, "user": "Honning"}, {"tags": {"building": "yes"}, "nodes": [{"lat": -1.1692888, "id": "4674894558", "lon": 34.3861357}, {"lat": -1.169303, "id": "4674894559", "lon": 34.3861624}, {"lat": -1.1693312, "id": "4674894560", "lon": 34.3861474}, {"lat": -1.1693171, "id": "4674894561", "lon": 34.3861208}, {"lat": -1.1692888, "id": "4674894558", "lon": 34.3861357}], "id": "473362793", "uid": "633013", "version": 1, "user": "Honning"}, {"tags": {"building": "yes"}, "nodes": [{"lat": -1.169263, "id": "4674894562", "lon": 34.3861504}, {"lat": -1.1692717, "id": "4674894563", "lon": 34.3861707}, {"lat": -1.1692881, "id": "4674894564", "lon": 34.3861637}, {"lat": -1.1692794, "id": "4674894565", "lon": 34.3861434}, {"lat": -1.169263, "id": "4674894562", "lon": 34.3861504}], "id": "473362794", "uid": "633013", "version": 1, "user": "Honning"}, {"tags": {"building": "yes"}, "nodes": [{"lat": -1.1691898, "id": "4674894566", "lon": 34.3861665}, {"lat": -1.1691973, "id": "4674894567", "lon": 34.386198}, {"lat": -1.1692402, "id": "4674894568", "lon": 34.3861877}, {"lat": -1.1692327, "id": "4674894569", "lon": 34.3861563}, {"lat": -1.1691898, "id": "4674894566", "lon": 34.3861665}], "id": "473362795", "uid": "633013", "version": 1, "user": "Honning"}, {"tags": {"building": "yes"}, "nodes": [{"lat": -1.1684723, "id": "4674894591", "lon": 34.3849502}, {"lat": -1.1684768, "id": "4674894592", "lon": 34.3849552}, {"lat": -1.1684795, "id": "4674894593", "lon": 34.3849613}, {"lat": -1.16848, "id": "4674894594", "lon": 34.384968}, {"lat": -1.1684784, "id": "4674894595", "lon": 34.3849746}, {"lat": -1.1684747, "id": "4674894596", "lon": 34.3849802}, {"lat": -1.1684694, "id": "4674894597", "lon": 34.3849844}, {"lat": -1.1684631, "id": "4674894598", "lon": 34.3849866}, {"lat": -1.1684564, "id": "4674894599", "lon": 34.3849867}, {"lat": -1.16845, "id": "4674894600", "lon": 34.3849847}, {"lat": -1.1684446, "id": "4674894601", "lon": 34.3849807}, {"lat": -1.1684408, "id": "4674894583", "lon": 34.3849751}, {"lat": -1.1684389, "id": "4674894586", "lon": 34.3849684}, {"lat": -1.1684394, "id": "4674894587", "lon": 34.3849615}, {"lat": -1.1684421, "id": "4674894588", "lon": 34.3849551}, {"lat": -1.1684468, "id": "4674894589", "lon": 34.38495}, {"lat": -1.1684529, "id": "4674894590", "lon": 34.3849467}, {"lat": -1.1684598, "id": "4674894584", "lon": 34.3849457}, {"lat": -1.1684664, "id": "4674894585", "lon": 34.3849469}, {"lat": -1.1684723, "id": "4674894591", "lon": 34.3849502}], "id": "473362796", "uid": "633013", "version": 1, "user": "Honning"}, {"tags": {"building": "yes"}, "nodes": [{"lat": -1.1683971, "id": "4674894602", "lon": 34.3849129}, {"lat": -1.1684119, "id": "4674894603", "lon": 34.3849435}, {"lat": -1.1684343, "id": "4674894604", "lon": 34.3849327}, {"lat": -1.1684194, "id": "4674894605", "lon": 34.384902}, {"lat": -1.1683971, "id": "4674894602", "lon": 34.3849129}], "id": "473362797", "uid": "633013", "version": 1, "user": "Honning"}, {"tags": {"building": "yes"}, "nodes": [{"lat": -1.1697943, "id": "4674894606", "lon": 34.386515}, {"lat": -1.1698095, "id": "4674894607", "lon": 34.3865412}, {"lat": -1.1698381, "id": "4674894608", "lon": 34.3865245}, {"lat": -1.1698229, "id": "4674894609", "lon": 34.3864984}, {"lat": -1.1697943, "id": "4674894606", "lon": 34.386515}], "id": "473362798", "uid": "633013", "version": 1, "user": "Honning"}, {"tags": {"building": "yes"}, "nodes": [{"lat": -1.1704704, "id": "4674894618", "lon": 34.3866813}, {"lat": -1.1704737, "id": "4674894619", "lon": 34.3866849}, {"lat": -1.1704756, "id": "4674894620", "lon": 34.3866893}, {"lat": -1.1704761, "id": "4674894621", "lon": 34.3866942}, {"lat": -1.170475, "id": "4674894622", "lon": 34.3866989}, {"lat": -1.1704724, "id": "4674894623", "lon": 34.386703}, {"lat": -1.1704687, "id": "4674894624", "lon": 34.3867061}, {"lat": -1.1704642, "id": "4674894625", "lon": 34.3867078}, {"lat": -1.1704593, "id": "4674894626", "lon": 34.3867081}, {"lat": -1.1704547, "id": "4674894627", "lon": 34.3867067}, {"lat": -1.1704507, "id": "4674894628", "lon": 34.386704}, {"lat": -1.1704478, "id": "4674894610", "lon": 34.3867001}, {"lat": -1.1704462, "id": "4674894613", "lon": 34.3866952}, {"lat": -1.1704464, "id": "4674894614", "lon": 34.38669}, {"lat": -1.1704483, "id": "4674894615", "lon": 34.3866852}, {"lat": -1.1704517, "id": "4674894616", "lon": 34.3866813}, {"lat": -1.1704563, "id": "4674894617", "lon": 34.3866789}, {"lat": -1.1704614, "id": "4674894611", "lon": 34.3866781}, {"lat": -1.1704662, "id": "4674894612", "lon": 34.386679}, {"lat": -1.1704704, "id": "4674894618", "lon": 34.3866813}], "id": "473362799", "uid": "633013", "version": 1, "user": "Honning"}, {"tags": {"building": "yes"}, "nodes": [{"lat": -1.170917, "id": "4674894629", "lon": 34.38613}, {"lat": -1.1709292, "id": "4674894630", "lon": 34.3861642}, {"lat": -1.1709669, "id": "4674894631", "lon": 34.3861507}, {"lat": -1.1709546, "id": "4674894632", "lon": 34.3861165}, {"lat": -1.170917, "id": "4674894629", "lon": 34.38613}], "id": "473362800", "uid": "633013", "version": 1, "user": "Honning"}, {"tags": {"building": "yes"}, "nodes": [{"lat": -1.1709365, "id": "4674894642", "lon": 34.3860947}, {"lat": -1.1709374, "id": "4674894643", "lon": 34.3860986}, {"lat": -1.1709369, "id": "4674894644", "lon": 34.3861026}, {"lat": -1.1709351, "id": "4674894645", "lon": 34.3861062}, {"lat": -1.1709322, "id": "4674894646", "lon": 34.3861089}, {"lat": -1.1709285, "id": "4674894647", "lon": 34.3861105}, {"lat": -1.1709245, "id": "4674894648", "lon": 34.3861107}, {"lat": -1.1709206, "id": "4674894649", "lon": 34.3861096}, {"lat": -1.1709174, "id": "4674894650", "lon": 34.3861072}, {"lat": -1.1709152, "id": "4674894651", "lon": 34.3861038}, {"lat": -1.1709143, "id": "4674894633", "lon": 34.3860999}, {"lat": -1.1709146, "id": "4674894636", "lon": 34.3860965}, {"lat": -1.1709159, "id": "4674894637", "lon": 34.3860933}, {"lat": -1.1709181, "id": "4674894638", "lon": 34.3860906}, {"lat": -1.170921, "id": "4674894639", "lon": 34.3860887}, {"lat": -1.1709244, "id": "4674894640", "lon": 34.3860877}, {"lat": -1.1709278, "id": "4674894641", "lon": 34.3860878}, {"lat": -1.1709311, "id": "4674894634", "lon": 34.3860889}, {"lat": -1.1709343, "id": "4674894635", "lon": 34.3860914}, {"lat": -1.1709365, "id": "4674894642", "lon": 34.3860947}], "id": "473362801", "uid": "633013", "version": 1, "user": "Honning"}, {"tags": {"building": "yes"}, "nodes": [{"lat": -1.1712609, "id": "4674894660", "lon": 34.386719}, {"lat": -1.1712656, "id": "4674894661", "lon": 34.3867229}, {"lat": -1.1712688, "id": "4674894662", "lon": 34.3867281}, {"lat": -1.1712701, "id": "4674894663", "lon": 34.3867341}, {"lat": -1.1712694, "id": "4674894664", "lon": 34.3867402}, {"lat": -1.1712668, "id": "4674894665", "lon": 34.3867457}, {"lat": -1.1712626, "id": "4674894666", "lon": 34.3867501}, {"lat": -1.1712571, "id": "4674894667", "lon": 34.3867529}, {"lat": -1.1712511, "id": "4674894668", "lon": 34.3867538}, {"lat": -1.1712451, "id": "4674894669", "lon": 34.3867527}, {"lat": -1.1712398, "id": "4674894670", "lon": 34.3867498}, {"lat": -1.1712356, "id": "4674894652", "lon": 34.3867452}, {"lat": -1.1712332, "id": "4674894655", "lon": 34.3867395}, {"lat": -1.1712328, "id": "4674894656", "lon": 34.3867332}, {"lat": -1.1712344, "id": "4674894657", "lon": 34.3867271}, {"lat": -1.171238, "id": "4674894658", "lon": 34.386722}, {"lat": -1.1712431, "id": "4674894659", "lon": 34.3867183}, {"lat": -1.1712491, "id": "4674894653", "lon": 34.3867165}, {"lat": -1.1712552, "id": "4674894654", "lon": 34.3867168}, {"lat": -1.1712609, "id": "4674894660", "lon": 34.386719}], "id": "473362802", "uid": "633013", "version": 1, "user": "Honning"}, {"tags": {"building": "yes"}, "nodes": [{"lat": -1.1713857, "id": "4674894679", "lon": 34.3864222}, {"lat": -1.171389, "id": "4674894680", "lon": 34.386428}, {"lat": -1.1713902, "id": "4674894681", "lon": 34.3864345}, {"lat": -1.1713893, "id": "4674894682", "lon": 34.3864411}, {"lat": -1.1713862, "id": "4674894683", "lon": 34.3864471}, {"lat": -1.1713814, "id": "4674894684", "lon": 34.3864517}, {"lat": -1.1713754, "id": "4674894685", "lon": 34.3864546}, {"lat": -1.1713687, "id": "4674894686", "lon": 34.3864553}, {"lat": -1.1713622, "id": "4674894687", "lon": 34.3864538}, {"lat": -1.1713566, "id": "4674894688", "lon": 34.3864503}, {"lat": -1.1713523, "id": "4674894789", "lon": 34.3864451}, {"lat": -1.17135, "id": "4674894671", "lon": 34.3864388}, {"lat": -1.1713498, "id": "4674894674", "lon": 34.3864321}, {"lat": -1.1713518, "id": "4674894675", "lon": 34.3864258}, {"lat": -1.1713558, "id": "4674894676", "lon": 34.3864204}, {"lat": -1.1713614, "id": "4674894677", "lon": 34.3864166}, {"lat": -1.1713678, "id": "4674894678", "lon": 34.3864148}, {"lat": -1.1713745, "id": "4674894672", "lon": 34.3864152}, {"lat": -1.1713807, "id": "4674894673", "lon": 34.3864178}, {"lat": -1.1713857, "id": "4674894679", "lon": 34.3864222}], "id": "473362803", "uid": "633013", "version": 1, "user": "Honning"}, {"tags": {"building": "yes"}, "nodes": [{"lat": -1.1714777, "id": "4674894790", "lon": 34.3856783}, {"lat": -1.171517, "id": "4674894791", "lon": 34.385695}, {"lat": -1.1715333, "id": "4674894792", "lon": 34.3856566}, {"lat": -1.171494, "id": "4674894793", "lon": 34.3856399}, {"lat": -1.1714777, "id": "4674894790", "lon": 34.3856783}], "id": "473362804", "uid": "633013", "version": 1, "user": "Honning"}, {"tags": {"building": "yes"}, "nodes": [{"lat": -1.1714922, "id": "4674894794", "lon": 34.385639}, {"lat": -1.1715324, "id": "4674894795", "lon": 34.3856548}, {"lat": -1.1715472, "id": "4674894796", "lon": 34.3856169}, {"lat": -1.171507, "id": "4674894797", "lon": 34.3856012}, {"lat": -1.1714922, "id": "4674894794", "lon": 34.385639}], "id": "473362805", "uid": "633013", "version": 1, "user": "Honning"}, {"tags": {"building": "yes"}, "nodes": [{"lat": -1.171565, "id": "4674894798", "lon": 34.3857005}, {"lat": -1.1716066, "id": "4674894799", "lon": 34.3857189}, {"lat": -1.1716258, "id": "4674894800", "lon": 34.3856755}, {"lat": -1.1715842, "id": "4674894801", "lon": 34.3856571}, {"lat": -1.171565, "id": "4674894798", "lon": 34.3857005}], "id": "473362806", "uid": "633013", "version": 1, "user": "Honning"}, {"tags": {"building": "yes"}, "nodes": [{"lat": -1.1695954, "id": "4674894802", "lon": 34.3827341}, {"lat": -1.1696184, "id": "4674894803", "lon": 34.38276}, {"lat": -1.1695925, "id": "4674894804", "lon": 34.3827831}, {"lat": -1.1695694, "id": "4674894805", "lon": 34.3827572}, {"lat": -1.1695954, "id": "4674894802", "lon": 34.3827341}], "id": "473362807", "uid": "633013", "version": 1, "user": "Honning"}, {"tags": {"building": "yes"}, "nodes": [{"lat": -1.1767354, "id": "4674894806", "lon": 34.3760156}, {"lat": -1.1767361, "id": "4674894807", "lon": 34.3760622}, {"lat": -1.1767839, "id": "4674894808", "lon": 34.3760616}, {"lat": -1.1767833, "id": "4674894809", "lon": 34.3760149}, {"lat": -1.1767354, "id": "4674894806", "lon": 34.3760156}], "id": "473362809", "uid": "633013", "version": 1, "user": "Honning"}, {"tags": {"building": "yes"}, "nodes": [{"lat": -1.1698276, "id": "4675182511", "lon": 34.3693346}, {"lat": -1.1698469, "id": "4675182512", "lon": 34.3693822}, {"lat": -1.16989, "id": "4675182513", "lon": 34.3693647}, {"lat": -1.1698707, "id": "4675182514", "lon": 34.3693172}, {"lat": -1.1698276, "id": "4675182511", "lon": 34.3693346}], "id": "473400860", "uid": "633013", "version": 1, "user": "Honning"}, {"tags": {"building": "yes"}, "nodes": [{"lat": -1.1821772, "id": "4675182577", "lon": 34.3778559}, {"lat": -1.1821868, "id": "4675182578", "lon": 34.3778904}, {"lat": -1.1822232, "id": "4675182579", "lon": 34.3778803}, {"lat": -1.1822136, "id": "4675182580", "lon": 34.3778458}, {"lat": -1.1821772, "id": "4675182577", "lon": 34.3778559}], "id": "473400863", "uid": "633013", "version": 1, "user": "Honning"}, {"tags": {"building": "yes"}, "nodes": [{"lat": -1.1826692, "id": "4675183861", "lon": 34.387242}, {"lat": -1.1826361, "id": "4675183862", "lon": 34.3873059}, {"lat": -1.1826814, "id": "4675183863", "lon": 34.3873294}, {"lat": -1.1827145, "id": "4675183864", "lon": 34.3872654}, {"lat": -1.1826692, "id": "4675183861", "lon": 34.387242}], "id": "473400868", "uid": "633013", "version": 1, "user": "Honning"}, {"tags": {"building": "yes"}, "nodes": [{"lat": -1.1826719, "id": "4675183865", "lon": 34.3872009}, {"lat": -1.1826932, "id": "4675183866", "lon": 34.3872406}, {"lat": -1.182722, "id": "4675183867", "lon": 34.3872251}, {"lat": -1.1827006, "id": "4675183868", "lon": 34.3871854}, {"lat": -1.1826719, "id": "4675183865", "lon": 34.3872009}], "id": "473400869", "uid": "633013", "version": 1, "user": "Honning"}, {"tags": {"building": "yes"}, "nodes": [{"lat": -1.1825939, "id": "4675183869", "lon": 34.3872875}, {"lat": -1.1825722, "id": "4675183870", "lon": 34.3873244}, {"lat": -1.1826045, "id": "4675183871", "lon": 34.3873434}, {"lat": -1.1826262, "id": "4675183872", "lon": 34.3873065}, {"lat": -1.1825939, "id": "4675183869", "lon": 34.3872875}], "id": "473400870", "uid": "633013", "version": 1, "user": "Honning"}, {"tags": {"building": "yes"}, "nodes": [{"lat": -1.1825171, "id": "4675183873", "lon": 34.3872185}, {"lat": -1.1825175, "id": "4675183874", "lon": 34.3872621}, {"lat": -1.182556, "id": "4675183875", "lon": 34.3872617}, {"lat": -1.1825556, "id": "4675183876", "lon": 34.3872181}, {"lat": -1.1825171, "id": "4675183873", "lon": 34.3872185}], "id": "473400871", "uid": "633013", "version": 1, "user": "Honning"}, {"tags": {"building": "yes"}, "nodes": [{"lat": -1.1826751, "id": "4675183886", "lon": 34.38716}, {"lat": -1.1826707, "id": "4675183887", "lon": 34.3871577}, {"lat": -1.1826657, "id": "4675183888", "lon": 34.3871571}, {"lat": -1.1826608, "id": "4675184089", "lon": 34.3871581}, {"lat": -1.1826565, "id": "4675184090", "lon": 34.3871606}, {"lat": -1.1826532, "id": "4675184091", "lon": 34.3871644}, {"lat": -1.1826514, "id": "4675184092", "lon": 34.3871691}, {"lat": -1.1826512, "id": "4675184093", "lon": 34.3871741}, {"lat": -1.1826527, "id": "4675184094", "lon": 34.3871789}, {"lat": -1.1826556, "id": "4675184095", "lon": 34.387183}, {"lat": -1.1826598, "id": "4675183877", "lon": 34.3871858}, {"lat": -1.1826645, "id": "4675183880", "lon": 34.3871872}, {"lat": -1.1826694, "id": "4675183881", "lon": 34.3871869}, {"lat": -1.1826739, "id": "4675183882", "lon": 34.3871851}, {"lat": -1.1826777, "id": "4675183883", "lon": 34.387182}, {"lat": -1.1826802, "id": "4675183884", "lon": 34.3871778}, {"lat": -1.1826813, "id": "4675183885", "lon": 34.387173}, {"lat": -1.1826808, "id": "4675183878", "lon": 34.3871681}, {"lat": -1.1826786, "id": "4675183879", "lon": 34.3871636}, {"lat": -1.1826751, "id": "4675183886", "lon": 34.38716}], "id": "473400872", "uid": "633013", "version": 1, "user": "Honning"}, {"tags": {"building": "yes"}, "nodes": [{"lat": -1.1724932, "id": "4675184106", "lon": 34.3761964}, {"lat": -1.1724976, "id": "4675184107", "lon": 34.3762022}, {"lat": -1.1724999, "id": "4675184108", "lon": 34.376209}, {"lat": -1.1724999, "id": "4675184109", "lon": 34.3762162}, {"lat": -1.1724975, "id": "4675184110", "lon": 34.376223}, {"lat": -1.1724931, "id": "4675184111", "lon": 34.3762287}, {"lat": -1.1724871, "id": "4675184112", "lon": 34.3762327}, {"lat": -1.1724801, "id": "4675184113", "lon": 34.3762344}, {"lat": -1.1724729, "id": "4675184114", "lon": 34.3762338}, {"lat": -1.1724663, "id": "4675184115", "lon": 34.3762309}, {"lat": -1.172461, "id": "4675184116", "lon": 34.3762261}, {"lat": -1.1724575, "id": "4675184098", "lon": 34.3762197}, {"lat": -1.1724563, "id": "4675184101", "lon": 34.3762126}, {"lat": -1.1724575, "id": "4675184102", "lon": 34.3762054}, {"lat": -1.1724609, "id": "4675184103", "lon": 34.376199}, {"lat": -1.1724663, "id": "4675184104", "lon": 34.3761941}, {"lat": -1.1724729, "id": "4675184105", "lon": 34.3761912}, {"lat": -1.1724802, "id": "4675184099", "lon": 34.3761907}, {"lat": -1.1724872, "id": "4675184100", "lon": 34.3761925}, {"lat": -1.1724932, "id": "4675184106", "lon": 34.3761964}], "id": "473400873", "uid": "633013", "version": 1, "user": "Honning"}, {"tags": {"building": "yes"}, "nodes": [{"lat": -1.1747335, "id": "4675347394", "lon": 34.3871334}, {"lat": -1.1747364, "id": "4675347395", "lon": 34.3871299}, {"lat": -1.174738, "id": "4675347396", "lon": 34.3871256}, {"lat": -1.1747381, "id": "4675347397", "lon": 34.3871211}, {"lat": -1.1747367, "id": "4675347398", "lon": 34.3871167}, {"lat": -1.1747339, "id": "4675347399", "lon": 34.3871131}, {"lat": -1.1747301, "id": "4675347400", "lon": 34.3871105}, {"lat": -1.1747257, "id": "4675347401", "lon": 34.3871094}, {"lat": -1.1747211, "id": "4675347402", "lon": 34.3871098}, {"lat": -1.174717, "id": "4675347403", "lon": 34.3871116}, {"lat": -1.1747136, "id": "4675347404", "lon": 34.3871148}, {"lat": -1.1747115, "id": "4675345986", "lon": 34.3871188}, {"lat": -1.1747108, "id": "4675347389", "lon": 34.3871232}, {"lat": -1.1747116, "id": "4675347390", "lon": 34.3871275}, {"lat": -1.1747136, "id": "4675347391", "lon": 34.3871314}, {"lat": -1.1747168, "id": "4675347392", "lon": 34.3871344}, {"lat": -1.1747208, "id": "4675347393", "lon": 34.3871363}, {"lat": -1.1747251, "id": "4675345987", "lon": 34.3871368}, {"lat": -1.1747296, "id": "4675345988", "lon": 34.3871358}, {"lat": -1.1747335, "id": "4675347394", "lon": 34.3871334}], "id": "473418073", "uid": "633013", "version": 1, "user": "Honning"}]